Workbook

Sheet GDP Total
B1: GeoName | C1: Unit | D1: 2012 | E1: 2013 | F1: 2014 | G1: 2015 | H1: 2016 | I1: 2017 | J1: 2018 | K1: 2019
A2: USA | B2: United States | C2: Millions of chained 2012 dollars | D2: 16197007 | E2: 16495369 | F2: 16912038 | G2: 17403843 | H2: 17688890 | I2: 18108082 | J2: 18638164 | K2: 19073056
A3: AL | B3: Alabama | C3: Millions of chained 2012 dollars | D3: 186299 | E3: 188165.1 | F3: 186849 | G3: 189339.1 | H3: 190703 | I3: 193023.9 | J3: 198435.9 | K3: 202940.3
A4: AK | B4: Alaska | C4: Millions of chained 2012 dollars | D4: 57670.1 | E4: 54750 | F4: 53273 | G4: 53798.7 | H4: 52710.7 | I4: 52727.4 | J4: 53092.4 | K4: 54442.9
A5: AZ | B5: Arizona | C5: Millions of chained 2012 dollars | D5: 268288.8 | E5: 270148.9 | F5: 273677.1 | G5: 280229.5 | H5: 289230.4 | I5: 299405.7 | J5: 311705.6 | K5: 321431.9
A6: AR | B6: Arkansas | C6: Millions of chained 2012 dollars | D6: 108745.2 | E6: 111778.9 | F6: 112932.1 | G6: 113860.9 | H6: 114541.2 | I6: 115346.7 | J6: 117293.8 | K6: 119443.4
A7: CA | B7: California | C7: Millions of chained 2012 dollars | D7: 2144497.3 | E7: 2220867.6 | F7: 2312540.1 | G7: 2428598.4 | H7: 2500950.4 | I7: 2610682.3 | J7: 2721651 | K7: 2792029.1
A8: CO | B8: Colorado | C8: Millions of chained 2012 dollars | D8: 273519.5 | E8: 282533.9 | F8: 295698.6 | G8: 309179.6 | H8: 316751.8 | I8: 329573.7 | J8: 341076.7 | K8: 353076.6
A9: CT | B9: Connecticut | C9: Millions of chained 2012 dollars | D9: 243801 | E9: 241081.2 | F9: 237784.3 | G9: 242910.7 | H9: 242793.9 | I9: 243682.5 | J9: 244925.7 | K9: 248818.7
A10: DE | B10: Delaware | C10: Millions of chained 2012 dollars | D10: 61975.8 | E10: 59157.1 | F10: 63499.5 | G10: 65876.1 | H10: 63108.7 | I10: 62740.1 | J10: 62764.7 | K10: 63280.2
A11: FL | B11: Florida | C11: Millions of chained 2012 dollars | D11: 769309.1 | E11: 784090.1 | F11: 805278 | G11: 839124.3 | H11: 866731 | I11: 896117 | J11: 924873.3 | K11: 950759.1
A12: GA | B12: Georgia | C12: Millions of chained 2012 dollars | D12: 444132.2 | E12: 450771.8 | F12: 465646 | G12: 481575.7 | H12: 498266.8 | I12: 516593.9 | J12: 528998.9 | K12: 539536.3
A13: HI | B13: Hawaii | C13: Millions of chained 2012 dollars | D13: 73582.7 | E13: 74277.5 | F13: 74529.3 | G13: 77185.4 | H13: 78905.1 | I13: 80715.8 | J13: 82651.9 | K13: 83509.4
... A52: WY | B52: Wyoming | C52: Millions of chained 2012 dollars | D52: 38431.7 | E52: 38503.9 | F52: 38717.6 | G52: 39723 | H52: 38052.9 | I52: 37997.1 | J52: 38040 | K52: 39306.6

Sheet GDP Per Cap
B1: GeoName | C1: Unit | D1: 2012 | E1: 2013 | F1: 2014 | G1: 2015 | H1: 2016 | I1: 2017 | J1: 2018 | K1: 2019
A2: USA | B2: United States | C2: Chained 2012 dollars | D2: 51611 | E2: 52202 | F2: 53132 | G2: 54279 | H2: 54774 | I2: 55720 | J2: 57052 | K2: 58107
A3: AL | B3: Alabama | C3: Chained 2012 dollars | D3: 38687 | E3: 38957 | F3: 38591 | G3: 39020 | H3: 39211 | I3: 39599 | J3: 40599 | K3: 41389
A4: AK | B4: Alaska | C4: Chained 2012 dollars | D4: 78952 | E4: 74281 | F4: 72354 | G4: 72948 | H4: 71091 | I4: 71282 | J4: 72221 | K4: 74422
A5: AZ | B5: Arizona | C5: Chained 2012 dollars | D5: 40929 | E5: 40729 | F5: 40663 | G5: 41031 | H5: 41669 | I5: 42505 | J5: 43546 | K5: 44161
A6: AR | B6: Arkansas | C6: Chained 2012 dollars | D6: 36836 | E6: 37771 | F6: 38058 | G6: 38233 | H6: 38309 | I6: 38432 | J6: 38971 | K6: 39580
A7: CA | B7: California | C7: Chained 2012 dollars | D7: 56510 | E7: 58046 | F7: 59915 | G7: 62403 | H7: 63853 | I7: 66331 | J7: 68970 | K7: 70662
A8: CO | B8: Colorado | C8: Chained 2012 dollars | D8: 52674 | E8: 53622 | F8: 55270 | G8: 56724 | H8: 57184 | I8: 58728 | J8: 59930 | K8: 61311
A9: CT | B9: Connecticut | C9: Chained 2012 dollars | D9: 67825 | E9: 67063 | F9: 66152 | G9: 67717 | H9: 67855 | I9: 68195 | J9: 68577 | K9: 69789
A10: DE | B10: Delaware | C10: Chained 2012 dollars | D10: 67720 | E10: 64052 | F10: 68097 | G10: 69988 | H10: 66506 | I10: 65571 | J10: 65009 | K10: 64985
A11: FL | B11: Florida | C11: Chained 2012 dollars | D11: 39865 | E11: 40116 | F11: 40577 | G11: 41522 | H11: 42047 | I11: 42746 | J11: 43535 | K11: 44267
A12: GA | B12: Georgia | C12: Chained 2012 dollars | D12: 44855 | E12: 45202 | F12: 46253 | G12: 47313 | H12: 48367 | I12: 49623 | J12: 50327 | K12: 50816
A13: HI | B13: Hawaii | C13: Chained 2012 dollars | D13: 52755 | E13: 52745 | F13: 52688 | G13: 54277 | H13: 55273 | I13: 56667 | J13: 58181 | K13: 58981
... A52: WY | B52: Wyoming | C52: Chained 2012 dollars | D52: 66686 | E52: 66144 | F52: 66464 | G52: 67831 | H52: 65135 | I52: 65633 | J52: 65859 | K52: 67915

Sheet TE Total
B1: 2012 | C1: 2013 | D1: 2014 | E1: 2015 | F1: 2016 | G1: 2017 | H1: 2018 | I1: 2019
A2: USA | B2: 6660.9051 | C2: 6845.4031 | D2: 6905.8513 | E2: 6736.2168 | F2: 6580.036 | G2: 6551.0271 | H2: 6752.7497 | I2: 6590.1289
A3: AL | B3: 150.38807 | C3: 148.86342 | D3: 151.48169 | E3: 145.13744 | F3: 138.3537 | G3: 133.17172 | H3: 138.6582 | I3: 131.57754
A4: AK | B4: 36.906666 | C4: 35.43779 | D4: 35.817569 | E4: 35.444297 | F4: 33.927278 | G4: 34.35099 | H4: 33.552197 | I4: 33.712165
A5: AZ | B5: 112.5873 | C5: 115.90833 | D5: 115.15233 | E5: 113.67137 | F5: 108.80397 | G5: 108.19075 | H5: 112.96584 | I5: 111.33995
A6: AR | B6: 98.31579 | C6: 97.694044 | D6: 100.3187 | E6: 89.607091 | F6: 92.325438 | G6: 92.668481 | H6: 100.94841 | I6: 92.226383
A7: CA | B7: 425.23812 | C7: 427.6142 | D7: 423.00819 | E7: 428.45857 | F7: 425.43379 | G7: 425.8619 | H7: 426.79358 | I7: 429.15727
A8: CO | B8: 132.80478 | C8: 131.21536 | D8: 132.37485 | E8: 130.21859 | F8: 129.01128 | G8: 129.94409 | H8: 130.50016 | I8: 133.24033
A9: CT | B9: 38.65432 | C9: 39.157446 | D9: 39.548551 | E9: 40.762597 | F9: 38.353037 | G9: 37.723317 | H9: 41.421079 | I9: 40.915546
A10: DE | B10: 16.036267 | C10: 15.756743 | D10: 15.606324 | E10: 15.834762 | F10: 16.787232 | G10: 15.456786 | H10: 15.763937 | I10: 15.306946
A11: FL | B11: 259.72173 | C11: 259.32358 | D11: 265.11367 | E11: 268.57413 | F11: 273.34216 | G11: 273.99884 | H11: 278.17235 | I11: 267.75146
A12: GA | B12: 160.46147 | C12: 162.79559 | D12: 168.28168 | E12: 167.27383 | F12: 165.42144 | G12: 162.99961 | H12: 163.89333 | I12: 157.49161
A13: HI | B13: 18.900461 | C13: 18.952821 | D13: 18.978988 | E13: 18.983333 | F13: 18.884045 | G13: 19.213709 | H13: 18.850494 | I13: 19.272415
... A52: WY | B52: 102.20906 | C52: 104.6291 | D52: 100.15791 | E52: 97.321246 | F52: 91.032638 | G52: 92.243461 | H52: 93.701425 | I52: 87.693749

Sheet TE Per Cap
B1: 2012 | C1: 2013 | D1: 2014 | E1: 2015 | F1: 2016 | G1: 2017 | H1: 2018 | I1: 2019
A2: USA | B2: ='TE Total'!B2/Population!G2*1000000 -> 21.224498 | C2: ='TE Total'!C2/Population!H2*1000000 -> 21.663099 | D2: ='TE Total'!D2/Population!I2*1000000 -> 21.695977 | E2: ='TE Total'!E2/Population!J2*1000000 -> 21.008977 | F2: ='TE Total'!F2/Population!K2*1000000 -> 20.375331 | G2: ='TE Total'!G2/Population!L2*1000000 -> 20.157904 | H2: ='TE Total'!H2/Population!M2*1000000 -> 20.670364 | I2: ='TE Total'!I2/Population!N2*1000000 -> 20.077195
A3: AL | B3: ='TE Total'!B3/Population!G3*1000000 -> 31.22943 | C3: ='TE Total'!C3/Population!H3*1000000 -> 30.820067 | D3: ='TE Total'!D3/Population!I3*1000000 -> 31.28624 | E3: ='TE Total'!E3/Population!J3*1000000 -> 29.910772 | F3: ='TE Total'!F3/Population!K3*1000000 -> 28.447207 | G3: ='TE Total'!G3/Population!L3*1000000 -> 27.320156 | H3: ='TE Total'!H3/Population!M3*1000000 -> 28.368914 | I3: ='TE Total'!I3/Population!N3*1000000 -> 26.835117
A4: AK | B4: ='TE Total'!B4/Population!G4*1000000 -> 50.526415 | C4: ='TE Total'!C4/Population!H4*1000000 -> 48.079404 | D4: ='TE Total'!D4/Population!I4*1000000 -> 48.646471 | E4: ='TE Total'!E4/Population!J4*1000000 -> 48.060195 | F4: ='TE Total'!F4/Population!K4*1000000 -> 45.757642 | G4: ='TE Total'!G4/Population!L4*1000000 -> 46.439084 | H4: ='TE Total'!H4/Population!M4*1000000 -> 45.640616 | I4: ='TE Total'!I4/Population!N4*1000000 -> 46.083514
A5: AZ | B5: ='TE Total'!B5/Population!G5*1000000 -> 17.175847 | C5: ='TE Total'!C5/Population!H5*1000000 -> 17.475117 | D5: ='TE Total'!D5/Population!I5*1000000 -> 17.109252 | E5: ='TE Total'!E5/Population!J5*1000000 -> 16.643743 | F5: ='TE Total'!F5/Population!K5*1000000 -> 15.675384 | G5: ='TE Total'!G5/Population!L5*1000000 -> 15.35926 | H5: ='TE Total'!H5/Population!M5*1000000 -> 15.781708 | I5: ='TE Total'!I5/Population!N5*1000000 -> 15.296645
A6: AR | B6: ='TE Total'!B6/Population!G6*1000000 -> 33.302957 | C6: ='TE Total'!C6/Population!H6*1000000 -> 33.011436 | D6: ='TE Total'!D6/Population!I6*1000000 -> 33.807027 | E6: ='TE Total'!E6/Population!J6*1000000 -> 30.089203 | F6: ='TE Total'!F6/Population!K6*1000000 -> 30.87892 | G6: ='TE Total'!G6/Population!L6*1000000 -> 30.875651 | H6: ='TE Total'!H6/Population!M6*1000000 -> 33.540654 | I6: ='TE Total'!I6/Population!N6*1000000 -> 30.56076
A7: CA | B7: ='TE Total'!B7/Population!G7*1000000 -> 11.205575 | C7: ='TE Total'!C7/Population!H7*1000000 -> 11.176304 | D7: ='TE Total'!D7/Population!I7*1000000 -> 10.959621 | E7: ='TE Total'!E7/Population!J7*1000000 -> 11.009252 | F7: ='TE Total'!F7/Population!K7*1000000 -> 10.862015 | G7: ='TE Total'!G7/Population!L7*1000000 -> 10.820075 | H7: ='TE Total'!H7/Population!M7*1000000 -> 10.815418 | I7: ='TE Total'!I7/Population!N7*1000000 -> 10.86138
A8: CO | B8: ='TE Total'!B8/Population!G8*1000000 -> 25.575546 | C8: ='TE Total'!C8/Population!H8*1000000 -> 24.903111 | D8: ='TE Total'!D8/Population!I8*1000000 -> 24.742496 | E8: ='TE Total'!E8/Population!J8*1000000 -> 23.890588 | F8: ='TE Total'!F8/Population!K8*1000000 -> 23.290534 | G8: ='TE Total'!G8/Population!L8*1000000 -> 23.155159 | H8: ='TE Total'!H8/Population!M8*1000000 -> 22.929815 | I8: ='TE Total'!I8/Population!N8*1000000 -> 23.137079
A9: CT | B9: ='TE Total'!B9/Population!G9*1000000 -> 10.7536 | C9: ='TE Total'!C9/Population!H9*1000000 -> 10.892678 | D9: ='TE Total'!D9/Population!I9*1000000 -> 11.002445 | E9: ='TE Total'!E9/Population!J9*1000000 -> 11.363594 | F9: ='TE Total'!F9/Population!K9*1000000 -> 10.718705 | G9: ='TE Total'!G9/Population!L9*1000000 -> 10.557006 | H9: ='TE Total'!H9/Population!M9*1000000 -> 11.597605 | I9: ='TE Total'!I9/Population!N9*1000000 -> 11.476088
A10: DE | B10: ='TE Total'!B10/Population!G10*1000000 -> 17.522547 | C10: ='TE Total'!C10/Population!H10*1000000 -> 17.060581 | D10: ='TE Total'!D10/Population!I10*1000000 -> 16.736238 | E10: ='TE Total'!E10/Population!J10*1000000 -> 16.823084 | F10: ='TE Total'!F10/Population!K10*1000000 -> 17.690864 | G10: ='TE Total'!G10/Population!L10*1000000 -> 16.154279 | H10: ='TE Total'!H10/Population!M10*1000000 -> 16.327581 | I10: ='TE Total'!I10/Population!N10*1000000 -> 15.719359
A11: FL | B11: ='TE Total'!B11/Population!G11*1000000 -> 13.458603 | C11: ='TE Total'!C11/Population!H11*1000000 -> 13.267605 | D11: ='TE Total'!D11/Population!I11*1000000 -> 13.358604 | E11: ='TE Total'!E11/Population!J11*1000000 -> 13.2898 | F11: ='TE Total'!F11/Population!K11*1000000 -> 13.260362 | G11: ='TE Total'!G11/Population!L11*1000000 -> 13.070211 | H11: ='TE Total'!H11/Population!M11*1000000 -> 13.093965 | I11: ='TE Total'!I11/Population!N11*1000000 -> 12.466465
A12: GA | B12: ='TE Total'!B12/Population!G12*1000000 -> 16.205888 | C12: ='TE Total'!C12/Population!H12*1000000 -> 16.324485 | D12: ='TE Total'!D12/Population!I12*1000000 -> 16.715708 | E12: ='TE Total'!E12/Population!J12*1000000 -> 16.434121 | F12: ='TE Total'!F12/Population!K12*1000000 -> 16.057388 | G12: ='TE Total'!G12/Population!L12*1000000 -> 15.657487 | H12: ='TE Total'!H12/Population!M12*1000000 -> 15.592359 | I12: ='TE Total'!I12/Population!N12*1000000 -> 14.833318
A13: HI | B13: ='TE Total'!B13/Population!G13*1000000 -> 13.550622 | C13: ='TE Total'!C13/Population!H13*1000000 -> 13.458488 | D13: ='TE Total'!D13/Population!I13*1000000 -> 13.417093 | E13: ='TE Total'!E13/Population!J13*1000000 -> 13.349254 | F13: ='TE Total'!F13/Population!K13*1000000 -> 13.228207 | G13: ='TE Total'!G13/Population!L13*1000000 -> 13.48905 | H13: ='TE Total'!H13/Population!M13*1000000 -> 13.269454 | I13: ='TE Total'!I13/Population!N13*1000000 -> 13.611693
... A52: WY | B52: ='TE Total'!B52/Population!G52*1000000 -> 177.35237 | C52: ='TE Total'!C52/Population!H52*1000000 -> 179.73741 | D52: ='TE Total'!D52/Population!I52*1000000 -> 171.93577 | E52: ='TE Total'!E52/Population!J52*1000000 -> 166.18696 | F52: ='TE Total'!F52/Population!K52*1000000 -> 155.82044 | G52: ='TE Total'!G52/Population!L52*1000000 -> 159.33412 | H52: ='TE Total'!H52/Population!M52*1000000 -> 162.22518 | I52: ='TE Total'!I52/Population!N52*1000000 -> 151.52032

Sheet CBE Total
B1: 2012 | C1: 2013 | D1: 2014 | E1: 2015 | F1: 2016 | G1: 2017 | H1: 2018 | I1: 2019
A2: USA | B2: 7400.7 | C2: 7535.1 | D2: 7731.2 | E2: 7686.9 | F2: 7616.2 | G2: 7473.3 | H2: 7725.6 | I2: 7550.1
A3: AL | B3: 119.30235 | C3: 120.7991 | D3: 123.32398 | E3: 123.36643 | F3: 118.80189 | G3: 114.09947 | H3: 119.32029 | I3: 114.79303
A4: AK | B4: 54.58811 | C4: 34.27874 | D4: 30.46932 | E4: 34.70093 | F4: 34.66121 | G4: 30.06314 | H4: 32.90498 | I4: 39.68367
A5: AZ | B5: 144.88303 | C5: 148.36082 | D5: 150.59351 | E5: 149.7335 | F5: 145.80704 | G5: 145.32879 | H5: 153.0599 | I5: 151.19086
A6: AR | B6: 74.79336 | C6: 74.26094 | D6: 75.46216 | E6: 71.79826 | F6: 73.01342 | G6: 72.38758 | H6: 76.24546 | I6: 71.69295
A7: CA | B7: 729.32918 | C7: 731.23727 | D7: 746.83965 | E7: 755.21781 | F7: 766.09104 | G7: 775.6175 | H7: 786.07674 | I7: 774.65486
A8: CO | B8: 143.37816 | C8: 147.49578 | D8: 150.37549 | E8: 152.69925 | F8: 151.8946 | G8: 155.29638 | H8: 159.47507 | I8: 158.80621
A9: CT | B9: 77.13963 | C9: 78.85843 | D9: 81.34803 | E9: 82.0224 | F9: 79.91544 | G9: 77.24412 | H9: 80.99358 | I9: 78.30809
A10: DE | B10: 21.42979 | C10: 21.65503 | D10: 21.51075 | E10: 21.68009 | F10: 21.77715 | G10: 21.35796 | H10: 22.23678 | I10: 21.42718
A11: FL | B11: 405.69256 | C11: 402.49683 | D11: 437.44147 | E11: 429.09437 | F11: 451.06485 | G11: 426.87781 | H11: 440.96505 | I11: 430.20764
A12: GA | B12: 224.06362 | C12: 206.21402 | D12: 217.75304 | E12: 215.71922 | F12: 216.49849 | G12: 212.31082 | H12: 218.92288 | I12: 214.00658
A13: HI | B13: 28.27411 | C13: 27.94494 | D13: 27.4355 | E13: 27.7138 | F13: 28.12317 | G13: 29.10051 | H13: 28.78991 | I13: 28.59157
... A52: WY | B52: 40.946 | C52: 41.83036 | D52: 40.71661 | E52: 40.59957 | F52: 36.74882 | G52: 36.94144 | H52: 38.15968 | I52: 35.66671
A53: Total | B53: =SUM(B3:B52) -> 7570.2939 | C53: =SUM(C3:C52) -> 7705.3334 | D53: =SUM(D3:D52) -> 7879.7862 | E53: =SUM(E3:E52) -> 7822.5677 | F53: =SUM(F3:F52) -> 7736.8961 | G53: =SUM(G3:G52) -> 7598.172 | H53: =SUM(H3:H52) -> 7860.9049 | I53: =SUM(I3:I52) -> 7668.0457
B55: Note: Difference between US reported by EPA and total from adding all states. See https://github.com/cornerstone-data/USEEIO-State/issues/6
A59: Global total | B59: 35000.02 | C59: 35301.655 | D59: 35450.094 | E59: 35404.9 | F59: 35416.658 | G59: 35989.897 | H59: 36730.425 | I59: 37104.275
A60: percent of total (CB) | B60: =B2/B59 -> 0.21144845 | C60: =C2/C59 -> 0.21344892 | D60: =D2/D59 -> 0.21808687 | E60: =E2/E59 -> 0.21711402 | F60: =F2/F59 -> 0.2150457 | G60: =G2/G59 -> 0.20764994 | H60: =H2/H59 -> 0.21033244 | I60: =I2/I59 -> 0.20348329
A61: percent of total (TE) | B61: ='TE Total'!B2/'CBE Total'!B59 -> 0.19031147 | C61: ='TE Total'!C2/'CBE Total'!C59 -> 0.19391168 | D61: ='TE Total'!D2/'CBE Total'!D59 -> 0.19480488 | E61: ='TE Total'!E2/'CBE Total'!E59 -> 0.19026227 | F61: ='TE Total'!F2/'CBE Total'!F59 -> 0.1857893 | G61: ='TE Total'!G2/'CBE Total'!G59 -> 0.18202406 | H61: ='TE Total'!H2/'CBE Total'!H59 -> 0.18384622 | I61: ='TE Total'!I2/'CBE Total'!I59 -> 0.17761104

Sheet CBE Per Cap
B1: ='CBE Total'!B1 -> 2012 | C1: ='CBE Total'!C1 -> 2013 | D1: ='CBE Total'!D1 -> 2014 | E1: ='CBE Total'!E1 -> 2015 | F1: ='CBE Total'!F1 -> 2016 | G1: ='CBE Total'!G1 -> 2017 | H1: ='CBE Total'!H1 -> 2018 | I1: ='CBE Total'!I1 -> 2019
A2: USA | B2: ='CBE Total'!B2/Population!G2*1000000 -> 23.581801 | C2: ='CBE Total'!C2/Population!H2*1000000 -> 23.845727 | D2: ='CBE Total'!D2/Population!I2*1000000 -> 24.288959 | E2: ='CBE Total'!E2/Population!J2*1000000 -> 23.973977 | F2: ='CBE Total'!F2/Population!K2*1000000 -> 23.583852 | G2: ='CBE Total'!G2/Population!L2*1000000 -> 22.995792 | H2: ='CBE Total'!H2/Population!M2*1000000 -> 23.648288 | I2: ='CBE Total'!I2/Population!N2*1000000 -> 23.0018
A3: AL | B3: ='CBE Total'!B3/Population!G3*1000000 -> 24.774202 | C3: ='CBE Total'!C3/Population!H3*1000000 -> 25.009746 | D3: ='CBE Total'!D3/Population!I3*1000000 -> 25.470694 | E3: ='CBE Total'!E3/Population!J3*1000000 -> 25.424074 | F3: ='CBE Total'!F3/Population!K3*1000000 -> 24.427116 | G3: ='CBE Total'!G3/Population!L3*1000000 -> 23.407487 | H3: ='CBE Total'!H3/Population!M3*1000000 -> 24.412454 | I3: ='CBE Total'!I3/Population!N3*1000000 -> 23.411931
A4: AK | B4: ='CBE Total'!B4/Population!G4*1000000 -> 74.732881 | C4: ='CBE Total'!C4/Population!H4*1000000 -> 46.506889 | D4: ='CBE Total'!D4/Population!I4*1000000 -> 41.382621 | E4: ='CBE Total'!E4/Population!J4*1000000 -> 47.052236 | F4: ='CBE Total'!F4/Population!K4*1000000 -> 46.747494 | G4: ='CBE Total'!G4/Population!L4*1000000 -> 40.642341 | H4: ='CBE Total'!H4/Population!M4*1000000 -> 44.760215 | I4: ='CBE Total'!I4/Population!N4*1000000 -> 54.246383
A5: AZ | B5: ='CBE Total'!B5/Population!G5*1000000 -> 22.102748 | C5: ='CBE Total'!C5/Population!H5*1000000 -> 22.367873 | D5: ='CBE Total'!D5/Population!I5*1000000 -> 22.375077 | E5: ='CBE Total'!E5/Population!J5*1000000 -> 21.923954 | F5: ='CBE Total'!F5/Population!K5*1000000 -> 21.006415 | G5: ='CBE Total'!G5/Population!L5*1000000 -> 20.631548 | H5: ='CBE Total'!H5/Population!M5*1000000 -> 21.382982 | I5: ='CBE Total'!I5/Population!N5*1000000 -> 20.771636
A6: AR | B6: ='CBE Total'!B6/Population!G6*1000000 -> 25.335097 | C6: ='CBE Total'!C6/Population!H6*1000000 -> 25.093242 | D6: ='CBE Total'!D6/Population!I6*1000000 -> 25.430466 | E6: ='CBE Total'!E6/Population!J6*1000000 -> 24.109168 | F6: ='CBE Total'!F6/Population!K6*1000000 -> 24.419874 | G6: ='CBE Total'!G6/Population!L6*1000000 -> 24.11838 | H6: ='CBE Total'!H6/Population!M6*1000000 -> 25.332965 | I6: ='CBE Total'!I6/Population!N6*1000000 -> 23.756662
A7: CA | B7: ='CBE Total'!B7/Population!G7*1000000 -> 19.218768 | C7: ='CBE Total'!C7/Population!H7*1000000 -> 19.111924 | D7: ='CBE Total'!D7/Population!I7*1000000 -> 19.349695 | E7: ='CBE Total'!E7/Population!J7*1000000 -> 19.405338 | F7: ='CBE Total'!F7/Population!K7*1000000 -> 19.559546 | G7: ='CBE Total'!G7/Population!L7*1000000 -> 19.706482 | H7: ='CBE Total'!H7/Population!M7*1000000 -> 19.920048 | I7: ='CBE Total'!I7/Population!N7*1000000 -> 19.605449
A8: CO | B8: ='CBE Total'!B8/Population!G8*1000000 -> 27.611767 | C8: ='CBE Total'!C8/Population!H8*1000000 -> 27.99294 | D8: ='CBE Total'!D8/Population!I8*1000000 -> 28.107038 | E8: ='CBE Total'!E8/Population!J8*1000000 -> 28.015009 | F8: ='CBE Total'!F8/Population!K8*1000000 -> 27.421683 | G8: ='CBE Total'!G8/Population!L8*1000000 -> 27.672766 | H8: ='CBE Total'!H8/Population!M8*1000000 -> 28.020915 | I8: ='CBE Total'!I8/Population!N8*1000000 -> 27.576574
A9: CT | B9: ='CBE Total'!B9/Population!G9*1000000 -> 21.460181 | C9: ='CBE Total'!C9/Population!H9*1000000 -> 21.936556 | D9: ='CBE Total'!D9/Population!I9*1000000 -> 22.631099 | E9: ='CBE Total'!E9/Population!J9*1000000 -> 22.865796 | F9: ='CBE Total'!F9/Population!K9*1000000 -> 22.334346 | G9: ='CBE Total'!G9/Population!L9*1000000 -> 21.617044 | H9: ='CBE Total'!H9/Population!M9*1000000 -> 22.677622 | I9: ='CBE Total'!I9/Population!N9*1000000 -> 21.964035
A10: DE | B10: ='CBE Total'!B10/Population!G10*1000000 -> 23.415955 | C10: ='CBE Total'!C10/Population!H10*1000000 -> 23.446939 | D10: ='CBE Total'!D10/Population!I10*1000000 -> 23.06815 | E10: ='CBE Total'!E10/Population!J10*1000000 -> 23.033247 | F10: ='CBE Total'!F10/Population!K10*1000000 -> 22.949381 | G10: ='CBE Total'!G10/Population!L10*1000000 -> 22.321746 | H10: ='CBE Total'!H10/Population!M10*1000000 -> 23.031863 | I10: ='CBE Total'!I10/Population!N10*1000000 -> 22.00449
A11: FL | B11: ='CBE Total'!B11/Population!G11*1000000 -> 21.022712 | C11: ='CBE Total'!C11/Population!H11*1000000 -> 20.592686 | D11: ='CBE Total'!D11/Population!I11*1000000 -> 22.041894 | E11: ='CBE Total'!E11/Population!J11*1000000 -> 21.232791 | F11: ='CBE Total'!F11/Population!K11*1000000 -> 21.882036 | G11: ='CBE Total'!G11/Population!L11*1000000 -> 20.362798 | H11: ='CBE Total'!H11/Population!M11*1000000 -> 20.756848 | I11: ='CBE Total'!I11/Population!N11*1000000 -> 20.030399
A12: GA | B12: ='CBE Total'!B12/Population!G12*1000000 -> 22.62942 | C12: ='CBE Total'!C12/Population!H12*1000000 -> 20.678311 | D12: ='CBE Total'!D12/Population!I12*1000000 -> 21.629783 | E12: ='CBE Total'!E12/Population!J12*1000000 -> 21.193726 | F12: ='CBE Total'!F12/Population!K12*1000000 -> 21.015415 | G12: ='CBE Total'!G12/Population!L12*1000000 -> 20.394245 | H12: ='CBE Total'!H12/Population!M12*1000000 -> 20.827719 | I12: ='CBE Total'!I12/Population!N12*1000000 -> 20.15617
A13: HI | B13: ='CBE Total'!B13/Population!G13*1000000 -> 20.271027 | C13: ='CBE Total'!C13/Population!H13*1000000 -> 19.843834 | D13: ='CBE Total'!D13/Population!I13*1000000 -> 19.395379 | E13: ='CBE Total'!E13/Population!J13*1000000 -> 19.488598 | F13: ='CBE Total'!F13/Population!K13*1000000 -> 19.700181 | G13: ='CBE Total'!G13/Population!L13*1000000 -> 20.430113 | H13: ='CBE Total'!H13/Population!M13*1000000 -> 20.266121 | I13: ='CBE Total'!I13/Population!N13*1000000 -> 20.193612
... A52: WY | B52: ='CBE Total'!B52/Population!G52*1000000 -> 71.049184 | C52: ='CBE Total'!C52/Population!H52*1000000 -> 71.858408 | D52: ='CBE Total'!D52/Population!I52*1000000 -> 69.89604 | E52: ='CBE Total'!E52/Population!J52*1000000 -> 69.328328 | F52: ='CBE Total'!F52/Population!K52*1000000 -> 62.902904 | G52: ='CBE Total'!G52/Population!L52*1000000 -> 63.809746 | H52: ='CBE Total'!H52/Population!M52*1000000 -> 66.065814 | I52: ='CBE Total'!I52/Population!N52*1000000 -> 61.626186
A53: Total | B53: ='CBE Total'!B53/Population!G2*1000000 -> 24.1222 | C53: ='CBE Total'!C53/Population!H2*1000000 -> 24.384451 | D53: ='CBE Total'!D53/Population!I2*1000000 -> 24.755769 | E53: ='CBE Total'!E53/Population!J2*1000000 -> 24.397099 | F53: ='CBE Total'!F53/Population!K2*1000000 -> 23.957592 | G53: ='CBE Total'!G53/Population!L2*1000000 -> 23.380031 | H53: ='CBE Total'!H53/Population!M2*1000000 -> 24.06246 | I53: ='CBE Total'!I53/Population!N2*1000000 -> 23.361129

Sheet Population
A1: Abbreviation | C1: Census | D1: Estimates Base | E1: 2010 | F1: 2011 | G1: 2012 | H1: 2013 | I1: 2014 | J1: 2015 | K1: 2016 | L1: 2017 | M1: 2018 | N1: 2019
A2: USA | B2: United States | C2: 308745538 | D2: 308758105 | E2: 309321666 | F2: 311556874 | G2: 313830990 | H2: 315993715 | I2: 318301008 | J2: 320635163 | K2: 322941311 | L2: 324985539 | M2: 326687501 | N2: 328239523
A3: AL | B3: .Alabama | C3: 4779736 | D3: 4780125 | E3: 4785437 | F3: 4799069 | G3: 4815588 | H3: 4830081 | I3: 4841799 | J3: 4852347 | K3: 4863525 | L3: 4874486 | M3: 4887681 | N3: 4903185
A4: AK | B4: .Alaska | C4: 710231 | D4: 710249 | E4: 713910 | F4: 722128 | G4: 730443 | H4: 737068 | I4: 736283 | J4: 737498 | K4: 741456 | L4: 739700 | M4: 735139 | N4: 731545
A5: AZ | B5: .Arizona | C5: 6392017 | D5: 6392288 | E5: 6407172 | F5: 6472643 | G5: 6554978 | H5: 6632764 | I5: 6730413 | J5: 6829676 | K5: 6941072 | L5: 7044008 | M5: 7158024 | N5: 7278717
A6: AR | B6: .Arkansas | C6: 2915918 | D6: 2916031 | E6: 2921964 | F6: 2940667 | G6: 2952164 | H6: 2959400 | I6: 2967392 | J6: 2978048 | K6: 2989918 | L6: 3001345 | M6: 3009733 | N6: 3017804
A7: CA | B7: .California | C7: 37253956 | D7: 37254519 | E7: 37319502 | F7: 37638369 | G7: 37948800 | H7: 38260787 | I7: 38596972 | J7: 38918045 | K7: 39167117 | L7: 39358497 | M7: 39461588 | N7: 39512223
A8: CO | B8: .Colorado | C8: 5029196 | D8: 5029319 | E8: 5047349 | F8: 5121108 | G8: 5192647 | H8: 5269035 | I8: 5350101 | J8: 5450623 | K8: 5539215 | L8: 5611885 | M8: 5691287 | N8: 5758736
A9: CT | B9: .Connecticut | C9: 3574097 | D9: 3574147 | E9: 3579114 | F9: 3588283 | G9: 3594547 | H9: 3594841 | I9: 3594524 | J9: 3587122 | K9: 3578141 | L9: 3573297 | M9: 3571520 | N9: 3565287
A10: DE | B10: .Delaware | C10: 897934 | D10: 897937 | E10: 899593 | F10: 907381 | G10: 915179 | H10: 923576 | I10: 932487 | J10: 941252 | K10: 948921 | L10: 956823 | M10: 965479 | N10: 973764
A11: FL | B11: .Florida | C11: 18801310 | D11: 18804564 | E11: 18845537 | F11: 19053237 | G11: 19297822 | H11: 19545621 | I11: 19845911 | J11: 20209042 | K11: 20613477 | L11: 20963613 | M11: 21244317 | N11: 21477737
A12: GA | B12: .Georgia | C12: 9687653 | D12: 9688729 | E12: 9711881 | F12: 9802431 | G12: 9901430 | H12: 9972479 | I12: 10067278 | J12: 10178447 | K12: 10301890 | L12: 10410330 | M12: 10511131 | N12: 10617423
A13: HI | B13: .Hawaii | C13: 1360301 | D13: 1360307 | E13: 1363963 | F13: 1379329 | G13: 1394804 | H13: 1408243 | I13: 1414538 | J13: 1422052 | K13: 1427559 | L13: 1424393 | M13: 1420593 | N13: 1415872
... A52: WY | B52: .Wyoming | C52: 563626 | D52: 563775 | E52: 564487 | F52: 567299 | G52: 576305 | H52: 582122 | I52: 582531 | J52: 585613 | K52: 584215 | L52: 578931 | M52: 577601 | N52: 578759
B54: .District of Columbia | C54: 601723 | D54: 601767 | E54: 605226 | F54: 619800 | G54: 634924 | H54: 650581 | I54: 662328 | J54: 675400 | K54: 685815 | L54: 694906 | M54: 701547 | N54: 705749
B55: Northeast | C55: 55317240 | D55: 55318443 | E55: 55380134 | F55: 55604223 | G55: 55775216 | H55: 55901806 | I55: 56006011 | J55: 56034684 | K55: 56042330 | L55: 56059240 | M55: 56046620 | N55: 55982803
B56: Midwest | C56: 66927001 | D56: 66929725 | E56: 66974416 | F56: 67157800 | G56: 67336743 | H56: 67560379 | I56: 67745167 | J56: 67860583 | K56: 67987540 | L56: 68126781 | M56: 68236628 | N56: 68329004
B57: South | C57: 114555744 | D57: 114563030 | E57: 114866680 | F57: 116006522 | G57: 117241208 | H57: 118364400 | I57: 119624037 | J57: 120997341 | K57: 122351760 | L57: 123542189 | M57: 124569433 | N57: 125580448
B58: West | C58: 71945553 | D58: 71946907 | E58: 72100436 | F58: 72788329 | G58: 73477823 | H58: 74167130 | I58: 74925793 | J58: 75742555 | K58: 76559681 | L58: 77257329 | M58: 77834820 | N58: 78347268
B59: Puerto Rico | C59: 3725789 | D59: 3726157 | E59: 3721525 | F59: 3678732 | G59: 3634488 | H59: 3593077 | I59: 3534874 | J59: 3473232 | K59: 3406672 | L59: 3325286 | M59: 3193354 | N59: 3193694
B60: Note: The estimates are based on the 2010 Census and reflect changes to the April 1, 2010 population due to the Count Question Resolution program and geographic program revisions. See Geographic Terms and Definitions at http://www.census.gov/programs-surveys/popest/guidance-geographies/terms-and-definitions.html for a list of the states that are included in each region. All geographic boundaries for the 2019 population estimates series except statistical area delineations are as of January 1, 2019. For population estimates methodology statements, see http://www.census.gov/programs-surveys/popest/technical-documentation/methodology.html.
B61: Suggested Citation:
B62: Table 1. Annual Estimates of the Resident Population for the United States, Regions, States, and Puerto Rico: April 1, 2010 to July 1, 2019 (NST-EST2019-01)
B63: Source: U.S. Census Bureau, Population Division
B64: Release Date: December 2019

Sheet Sectoral Data
A1: California All Sectors (2019, aggregated) | F1: California Manufacturing Sector (2019) | K1: California All Sectors (2019, full)
A2: Description | B2: NAICS ID | C2: Location | D2: MMT GHG | F2: Desctiption | G2: Location | H2: NAICS ID | I2: MMT GHG | K2: Description | L2: NAICS ID | M2: Location | N2: MMT GHG
A4: Agriculture, Forestry, Fishing and Hunting | B4: 11 | C4: RoUS | D4: 3.537943 | F4: =VLOOKUP(H4, 'Sector Codes'!B$2:C$74, 2, FALSE) -> Wood products (e.g. plywood, veneer) | G4: US-CA | H4: 321 | I4: 0.15900079 | K4: US-CA | L4: Oilseeds, grains, vegetables, fruits, animal farms and aquaculture | M4: Agriculture | N4: 5.2151
A5: Agriculture, Forestry, Fishing and Hunting | B5: 11 | C5: RoW | D5: 3.287498 | F5: =VLOOKUP(H5, 'Sector Codes'!B$2:C$74, 2, FALSE) -> Clay, glass, cement, concrete, and other nonmetallic mineral products | G5: US-CA | H5: 327 | I5: 0.41230007 | K5: RoUS | L5: Oilseeds, grains, vegetables, fruits, animal farms and aquaculture | M5: Agriculture | N5: 3.6813593
A6: Agriculture, Forestry, Fishing and Hunting | B6: 11 | C6: CA | D6: 5.747798 | F6: =VLOOKUP(H6, 'Sector Codes'!B$2:C$74, 2, FALSE) -> Primary and secondary ferrous and nonferrous metals | G6: US-CA | H6: 331 | I6: 0.02211315 | K6: RoW | L6: Oilseeds, grains, vegetables, fruits, animal farms and aquaculture | M6: Agriculture | N6: 2.0466915
A7: Mining | B7: 21 | C7: RoUS | D7: 0.01224182 | F7: =VLOOKUP(H7, 'Sector Codes'!B$2:C$74, 2, FALSE) -> Fabricated metal products (e.g. architectural and structural metal products) | G7: US-CA | H7: 332 | I7: 0.57845232 | K7: US-CA | L7: Raw forest products, wild-caught fish and game, agriculture and forestry support | M7: Agriculture | N7: 0.069756668
A8: Mining | B8: 21 | C8: RoW | D8: 0.08364578 | F8: =VLOOKUP(H8, 'Sector Codes'!B$2:C$74, 2, FALSE) -> Machinery (except computers) | G8: US-CA | H8: 333 | I8: 2.7811823 | K8: RoUS | L8: Raw forest products, wild-caught fish and game, agriculture and forestry support | M8: Agriculture | N8: 0.019924351
A9: Mining | B9: 21 | C9: CA | D9: 1.908155 | F9: =VLOOKUP(H9, 'Sector Codes'!B$2:C$74, 2, FALSE) -> Computers and relevant parts, conductors, measuring devices, communication devices | G9: US-CA | H9: 334 | I9: 2.2469007 | K9: RoW | L9: Raw forest products, wild-caught fish and game, agriculture and forestry support | M9: Agriculture | N9: 0.083759635
A10: Utilities | B10: 22 | C10: RoUS | D10: 10.10205 | F10: =VLOOKUP(H10, 'Sector Codes'!B$2:C$74, 2, FALSE) -> Lights and light fixtures, switch boards, transformers, and home appliances | G10: US-CA | H10: 335 | I10: 0.53732803 | K10: US-CA | L10: Unrefined oil and gas | M10: Mining | N10: 0
A11: Utilities | B11: 22 | C11: RoW | D11: 0.2768875 | F11: =VLOOKUP(H11, 'Sector Codes'!B$2:C$74, 2, FALSE) -> On-road vehicles (excluding motorcycles) and accompanying parts | G11: US-CA | H11: 3361MV | I11: 1.6742462 | K11: RoUS | L11: Unrefined oil and gas | M11: Mining | N11: 0
A12: Utilities | B12: 22 | C12: CA | D12: 24.79594 | F12: =VLOOKUP(H12, 'Sector Codes'!B$2:C$74, 2, FALSE) -> Other vehicles (e.g. aircraft, water vessels), missiles, and accompanying parts | G12: US-CA | H12: 3364OT | I12: 1.8279243 | K12: RoW | L12: Unrefined oil and gas | M12: Mining | N12: 0
A13: Construction | B13: 23 | C13: RoUS | D13: 0 | F13: =VLOOKUP(H13, 'Sector Codes'!B$2:C$74, 2, FALSE) -> Furniture and shelving | G13: US-CA | H13: 337 | I13: 1.3976323 | K13: US-CA | L13: Metal ores, dimensional stone, nonmetallic minerals | M13: Mining | N13: 0.0034554144
A14: Construction | B14: 23 | C14: RoW | D14: 0 | F14: =VLOOKUP(H14, 'Sector Codes'!B$2:C$74, 2, FALSE) -> Medical supplies, entertainment and sporting goods, fashion goods, advertising products | G14: US-CA | H14: 339 | I14: 1.9574654 | K14: RoUS | L14: Metal ores, dimensional stone, nonmetallic minerals | M14: Mining | N14: 0.0096671594
A15: Construction | B15: 23 | C15: CA | D15: 48.33492 | F15: =VLOOKUP(H15, 'Sector Codes'!B$2:C$74, 2, FALSE) -> Food and beverage and tobacco products | G15: US-CA | H15: 311FT | I15: 30.623202 | K15: RoW | L15: Metal ores, dimensional stone, nonmetallic minerals | M15: Mining | N15: 0.015017353
A16: Manufacturing | B16: 31G | C16: RoUS | D16: 35.17649 | F16: =VLOOKUP(H16, 'Sector Codes'!B$2:C$74, 2, FALSE) -> Textiles and textile-derived products (except clothes) | G16: US-CA | H16: 313TT | I16: 0.45330283 | K16: US-CA | L16: Well drilling and support activities for mining | M16: Mining | N16: 3.394944
A17: Manufacturing | B17: 31G | C17: RoW | D17: 91.32332 | F17: =VLOOKUP(H17, 'Sector Codes'!B$2:C$74, 2, FALSE) -> Clothing and leather | G17: US-CA | H17: 315AL | I17: 0.23708066 | K17: RoUS | L17: Well drilling and support activities for mining | M17: Mining | N17: 0.026641985
A18: Manufacturing | B18: 31G | C18: CA | D18: 70.77659 | F18: =VLOOKUP(H18, 'Sector Codes'!B$2:C$74, 2, FALSE) -> Paper products and paper production facilities | G18: US-CA | H18: 322 | I18: 1.0402425 | K18: RoW | L18: Well drilling and support activities for mining | M18: Mining | N18: 0.1311828
A19: Wholesale | B19: 42 | C19: RoUS | D19: 10.67734 | F19: =VLOOKUP(H19, 'Sector Codes'!B$2:C$74, 2, FALSE) -> Print media and printing support | G19: US-CA | H19: 323 | I19: 0.11482156 | K19: US-CA | L19: Electricity, natural gas, drinking water, and wastewater treatment | M19: Utilities | N19: 30.869235
A20: Wholesale | B20: 42 | C20: RoW | D20: 0 | F20: =VLOOKUP(H20, 'Sector Codes'!B$2:C$74, 2, FALSE) -> Petroleum fuels, asphalt, and other petroleum and coal products | G20: US-CA | H20: 324 | I20: 21.842538 | K20: RoUS | L20: Electricity, natural gas, drinking water, and wastewater treatment | M20: Utilities | N20: 20.445456
A21: Wholesale | B21: 42 | C21: CA | D21: 2.958552 | F21: =VLOOKUP(H21, 'Sector Codes'!B$2:C$74, 2, FALSE) -> Agricultural, pharmaceutical, industrial, and commercial chemicals | G21: US-CA | H21: 325 | I21: 6.202445 | K21: RoW | L21: Electricity, natural gas, drinking water, and wastewater treatment | M21: Utilities | N21: 0.1992872
A22: Retail | B22: 44RT | C22: RoUS | D22: 3.087364 | F22: =VLOOKUP(H22, 'Sector Codes'!B$2:C$74, 2, FALSE) -> Plastics and rubber products | G22: US-CA | H22: 326 | I22: 0.4913064 | K22: US-CA | L22: Construction | M22: Construction | N22: 36.878671
A23: Retail | B23: 44RT | C23: RoW | D23: 0 | F23: =VLOOKUP(H23, 'Sector Codes'!B$2:C$74, 2, FALSE) -> Wood products (e.g. plywood, veneer) | G23: RoUS | H23: 321 | I23: 0.13295289 | K23: RoUS | L23: Construction | M23: Construction | N23: 0
A24: Retail | B24: 44RT | C24: CA | D24: 18.598 | F24: =VLOOKUP(H24, 'Sector Codes'!B$2:C$74, 2, FALSE) -> Clay, glass, cement, concrete, and other nonmetallic mineral products | G24: RoUS | H24: 327 | I24: 0.17538526 | K24: RoW | L24: Construction | M24: Construction | N24: 0
A25: Transport/Warehouse | B25: 48TW | C25: RoUS | D25: 14.82118 | F25: =VLOOKUP(H25, 'Sector Codes'!B$2:C$74, 2, FALSE) -> Primary and secondary ferrous and nonferrous metals | G25: RoUS | H25: 331 | I25: 0.02426904 | K25: US-CA | L25: Food and beverage and tobacco products | M25: Manufacturing | N25: 30.623202
A26: Transport/Warehouse | B26: 48TW | C26: RoW | D26: 5.853901 | F26: =VLOOKUP(H26, 'Sector Codes'!B$2:C$74, 2, FALSE) -> Fabricated metal products (e.g. architectural and structural metal products) | G26: RoUS | H26: 332 | I26: 0.39599766 | K26: RoUS | L26: Food and beverage and tobacco products | M26: Manufacturing | N26: 17.826563
A27: Transport/Warehouse | B27: 48TW | C27: CA | D27: 26.61868 | F27: =VLOOKUP(H27, 'Sector Codes'!B$2:C$74, 2, FALSE) -> Machinery (except computers) | G27: RoUS | H27: 333 | I27: 1.829632 | K27: RoW | L27: Food and beverage and tobacco products | M27: Manufacturing | N27: 5.8406934
A28: Information | B28: 51 | C28: RoUS | D28: 4.745767 | F28: =VLOOKUP(H28, 'Sector Codes'!B$2:C$74, 2, FALSE) -> Computers and relevant parts, conductors, measuring devices, communication devices | G28: RoUS | H28: 334 | I28: 1.3961011 | K28: US-CA | L28: Textiles and textile-derived products (except clothes) | M28: Manufacturing | N28: 0.45330283
A29: Information | B29: 51 | C29: RoW | D29: 0.1429581 | F29: =VLOOKUP(H29, 'Sector Codes'!B$2:C$74, 2, FALSE) -> Lights and light fixtures, switch boards, transformers, and home appliances | G29: RoUS | H29: 335 | I29: 0.97589828 | K29: RoUS | L29: Textiles and textile-derived products (except clothes) | M29: Manufacturing | N29: 0.53253038
A30: Information | B30: 51 | C30: CA | D30: 5.574468 | F30: =VLOOKUP(H30, 'Sector Codes'!B$2:C$74, 2, FALSE) -> On-road vehicles (excluding motorcycles) and accompanying parts | G30: RoUS | H30: 3361MV | I30: 4.9715159 | K30: RoW | L30: Textiles and textile-derived products (except clothes) | M30: Manufacturing | N30: 1.3828802
A31: Education and Healthcare | B31: 6 | C31: RoUS | D31: 7.202512 | F31: =VLOOKUP(H31, 'Sector Codes'!B$2:C$74, 2, FALSE) -> Other vehicles (e.g. aircraft, water vessels), missiles, and accompanying parts | G31: RoUS | H31: 3364OT | I31: 1.0849556 | K31: US-CA | L31: Clothing and leather | M31: Manufacturing | N31: 0.23708066
A32: Education and Healthcare | B32: 6 | C32: RoW | D32: 0.02048244 | F32: =VLOOKUP(H32, 'Sector Codes'!B$2:C$74, 2, FALSE) -> Furniture and shelving | G32: RoUS | H32: 337 | I32: 0.53810555 | K32: RoUS | L32: Clothing and leather | M32: Manufacturing | N32: 0.13666721
A33: Education and Healthcare | B33: 6 | C33: CA | D33: 45.58908 | F33: =VLOOKUP(H33, 'Sector Codes'!B$2:C$74, 2, FALSE) -> Medical supplies, entertainment and sporting goods, fashion goods, advertising products | G33: RoUS | H33: 339 | I33: 0.76371388 | K33: RoW | L33: Clothing and leather | M33: Manufacturing | N33: 14.826666
A34: Entertainment, Accomodation, and Food Services | B34: 7 | C34: RoUS | D34: 9.837503 | F34: =VLOOKUP(H34, 'Sector Codes'!B$2:C$74, 2, FALSE) -> Food and beverage and tobacco products | G34: RoUS | H34: 311FT | I34: 17.826563 | K34: US-CA | L34: Wood products (e.g. plywood, veneer) | M34: Manufacturing | N34: 0.15900079
A35: Entertainment, Accomodation, and Food Services | B35: 7 | C35: RoW | D35: 0.01933733 | F35: =VLOOKUP(H35, 'Sector Codes'!B$2:C$74, 2, FALSE) -> Textiles and textile-derived products (except clothes) | G35: RoUS | H35: 313TT | I35: 0.53253038 | K35: RoUS | L35: Wood products (e.g. plywood, veneer) | M35: Manufacturing | N35: 0.13295289
A36: Entertainment, Accomodation, and Food Services | B36: 7 | C36: CA | D36: 22.92217 | F36: =VLOOKUP(H36, 'Sector Codes'!B$2:C$74, 2, FALSE) -> Clothing and leather | G36: RoUS | H36: 315AL | I36: 0.13666721 | K36: RoW | L36: Wood products (e.g. plywood, veneer) | M36: Manufacturing | N36: 0.11657182
A37: Other Services | B37: 81 | C37: RoUS | D37: 1.994856 | F37: =VLOOKUP(H37, 'Sector Codes'!B$2:C$74, 2, FALSE) -> Paper products and paper production facilities | G37: RoUS | H37: 322 | I37: 0.97346971 | K37: US-CA | L37: Paper products and paper production facilities | M37: Manufacturing | N37: 1.0402425
A38: Other Services | B38: 81 | C38: RoW | D38: 0.0333751 | F38: =VLOOKUP(H38, 'Sector Codes'!B$2:C$74, 2, FALSE) -> Print media and printing support | G38: RoUS | H38: 323 | I38: 0.08425397 | K38: RoUS | L38: Paper products and paper production facilities | M38: Manufacturing | N38: 0.97346971
A39: Other Services | B39: 81 | C39: CA | D39: 8.495983 | F39: =VLOOKUP(H39, 'Sector Codes'!B$2:C$74, 2, FALSE) -> Petroleum fuels, asphalt, and other petroleum and coal products | G39: RoUS | H39: 324 | I39: 2.7266623 | K39: RoW | L39: Paper products and paper production facilities | M39: Manufacturing | N39: 0.14225897
A40: Direct Household Emissions (e.g. fuel burned in private vehicles) | B40: F010-Mobile | C40: RoW | D40: 0 | F40: =VLOOKUP(H40, 'Sector Codes'!B$2:C$74, 2, FALSE) -> Agricultural, pharmaceutical, industrial, and commercial chemicals | G40: RoUS | H40: 325 | I40: 4.0841688 | K40: US-CA | L40: Print media and printing support | M40: Manufacturing | N40: 0.11482156
A41: Direct Household Emissions (e.g. fuel burned in private vehicles) | B41: F010-Mobile | C41: RoUS | D41: 0 | F41: =VLOOKUP(H41, 'Sector Codes'!B$2:C$74, 2, FALSE) -> Plastics and rubber products | G41: RoUS | H41: 326 | I41: 0.48934814 | K41: RoUS | L41: Print media and printing support | M41: Manufacturing | N41: 0.084253969
A42: Direct Household Emissions (e.g. fuel burned in private vehicles) | B42: F010-Mobile | C42: CA | D42: 113.18155 | F42: =VLOOKUP(H42, 'Sector Codes'!B$2:C$74, 2, FALSE) -> Wood products (e.g. plywood, veneer) | G42: RoW | H42: 321 | I42: 0.11657182 | K42: RoW | L42: Print media and printing support | M42: Manufacturing | N42: 0.027219124
A43: Direct Household Emissions (e.g. fuel burned in private homes) | B43: F010-Stationary | C43: RoW | D43: 0 | F43: =VLOOKUP(H43, 'Sector Codes'!B$2:C$74, 2, FALSE) -> Clay, glass, cement, concrete, and other nonmetallic mineral products | G43: RoW | H43: 327 | I43: 0.61933198 | K43: US-CA | L43: Petroleum fuels, asphalt, and other petroleum and coal products | M43: Manufacturing | N43: 21.842538
A44: Direct Household Emissions (e.g. fuel burned in private homes) | B44: F010-Stationary | C44: RoUS | D44: 0 | F44: =VLOOKUP(H44, 'Sector Codes'!B$2:C$74, 2, FALSE) -> Primary and secondary ferrous and nonferrous metals | G44: RoW | H44: 331 | I44: 0.01182415 | K44: RoUS | L44: Petroleum fuels, asphalt, and other petroleum and coal products | M44: Manufacturing | N44: 2.7266623
A45: Direct Household Emissions (e.g. fuel burned in private homes) | B45: F010-Stationary | C45: CA | D45: 31.056353 | F45: =VLOOKUP(H45, 'Sector Codes'!B$2:C$74, 2, FALSE) -> Fabricated metal products (e.g. architectural and structural metal products) | G45: RoW | H45: 332 | I45: 1.100583 | K45: RoW | L45: Petroleum fuels, asphalt, and other petroleum and coal products | M45: Manufacturing | N45: 1.6228214
A46: Finance, Insurance, and Real Estate | B46: FIRE | C46: RoUS | D46: 8.35268 | F46: =VLOOKUP(H46, 'Sector Codes'!B$2:C$74, 2, FALSE) -> Machinery (except computers) | G46: RoW | H46: 333 | I46: 2.8906219 | K46: US-CA | L46: Agricultural, pharmaceutical, industrial, and commercial chemicals | M46: Manufacturing | N46: 6.202445
A47: Finance, Insurance, and Real Estate | B47: FIRE | C47: RoW | D47: 0.0172417 | F47: =VLOOKUP(H47, 'Sector Codes'!B$2:C$74, 2, FALSE) -> Computers and relevant parts, conductors, measuring devices, communication devices | G47: RoW | H47: 334 | I47: 30.263515 | K47: RoUS | L47: Agricultural, pharmaceutical, industrial, and commercial chemicals | M47: Manufacturing | N47: 4.0841688
A48: Finance, Insurance, and Real Estate | B48: FIRE | C48: CA | D48: 18.63725 | F48: =VLOOKUP(H48, 'Sector Codes'!B$2:C$74, 2, FALSE) -> Lights and light fixtures, switch boards, transformers, and home appliances | G48: RoW | H48: 335 | I48: 2.6022672 | K48: RoW | L48: Agricultural, pharmaceutical, industrial, and commercial chemicals | M48: Manufacturing | N48: 9.3975907
A49: Government | B49: G | C49: RoUS | D49: 0.1665817 | F49: =VLOOKUP(H49, 'Sector Codes'!B$2:C$74, 2, FALSE) -> On-road vehicles (excluding motorcycles) and accompanying parts | G49: RoW | H49: 3361MV | I49: 5.0190148 | K49: US-CA | L49: Plastics and rubber products | M49: Manufacturing | N49: 0.4913064
A50: Government | B50: G | C50: RoW | D50: 0.0003725958 | F50: =VLOOKUP(H50, 'Sector Codes'!B$2:C$74, 2, FALSE) -> Other vehicles (e.g. aircraft, water vessels), missiles, and accompanying parts | G50: RoW | H50: 3364OT | I50: 0.70997256 | K50: RoUS | L50: Plastics and rubber products | M50: Manufacturing | N50: 0.48934814
A51: Government | B51: G | C51: CA | D51: 87.44339 | F51: =VLOOKUP(H51, 'Sector Codes'!B$2:C$74, 2, FALSE) -> Furniture and shelving | G51: RoW | H51: 337 | I51: 3.2957659 | K51: RoW | L51: Plastics and rubber products | M51: Manufacturing | N51: 1.1372497
A52: Used/other? | B52: PROF | C52: RoUS | D52: 18.62136 | F52: =VLOOKUP(H52, 'Sector Codes'!B$2:C$74, 2, FALSE) -> Medical supplies, entertainment and sporting goods, fashion goods, advertising products | G52: RoW | H52: 339 | I52: 5.6985407 | K52: US-CA | L52: Clay, glass, cement, concrete, and other nonmetallic mineral products | M52: Manufacturing | N52: 0.41230007
A53: Used/other? | B53: PROF | C53: RoW | D53: 2.073201 | F53: =VLOOKUP(H53, 'Sector Codes'!B$2:C$74, 2, FALSE) -> Food and beverage and tobacco products | G53: RoW | H53: 311FT | I53: 5.8406934 | K53: RoUS | L53: Clay, glass, cement, concrete, and other nonmetallic mineral products | M53: Manufacturing | N53: 0.17538526
A54: Used/other? | B54: PROF | C54: CA | D54: 8.808773 | F54: =VLOOKUP(H54, 'Sector Codes'!B$2:C$74, 2, FALSE) -> Textiles and textile-derived products (except clothes) | G54: RoW | H54: 313TT | I54: 1.3828802 | K54: RoW | L54: Clay, glass, cement, concrete, and other nonmetallic mineral products | M54: Manufacturing | N54: 0.61933198
D55: =SUM(D4:D54) -> 772.91574 | F55: =VLOOKUP(H55, 'Sector Codes'!B$2:C$74, 2, FALSE) -> Clothing and leather | G55: RoW | H55: 315AL | I55: 14.826666 | K55: US-CA | L55: Primary and secondary ferrous and nonferrous metals | M55: Manufacturing | N55: 0.022113154
A56: Note: CBE emissions occuring in CA are greater than TE! This is not possible. See Wesley's (incomplete) explanation here https://github.com/cornerstone-data/USEEIO-State/issues/1 | F56: =VLOOKUP(H56, 'Sector Codes'!B$2:C$74, 2, FALSE) -> Paper products and paper production facilities | G56: RoW | H56: 322 | I56: 0.14225897 | K56: RoUS | L56: Primary and secondary ferrous and nonferrous metals | M56: Manufacturing | N56: 0.024269035
F57: =VLOOKUP(H57, 'Sector Codes'!B$2:C$74, 2, FALSE) -> Print media and printing support | G57: RoW | H57: 323 | I57: 0.02721912 | K57: RoW | L57: Primary and secondary ferrous and nonferrous metals | M57: Manufacturing | N57: 0.01182415
F58: =VLOOKUP(H58, 'Sector Codes'!B$2:C$74, 2, FALSE) -> Petroleum fuels, asphalt, and other petroleum and coal products | G58: RoW | H58: 324 | I58: 1.6228214 | K58: US-CA | L58: Fabricated metal products (e.g. architectural and structural metal products) | M58: Manufacturing | N58: 0.57845232
F59: =VLOOKUP(H59, 'Sector Codes'!B$2:C$74, 2, FALSE) -> Agricultural, pharmaceutical, industrial, and commercial chemicals | G59: RoW | H59: 325 | I59: 9.3975907 | K59: RoUS | L59: Fabricated metal products (e.g. architectural and structural metal products) | M59: Manufacturing | N59: 0.39599766
F60: =VLOOKUP(H60, 'Sector Codes'!B$2:C$74, 2, FALSE) -> Plastics and rubber products | G60: RoW | H60: 326 | I60: 1.1372497 | K60: RoW | L60: Fabricated metal products (e.g. architectural and structural metal products) | M60: Manufacturing | N60: 1.100583
K61: US-CA | L61: Machinery (except computers) | M61: Manufacturing | N61: 2.7811823
K62: RoUS | L62: Machinery (except computers) | M62: Manufacturing | N62: 1.829632
K63: RoW | L63: Machinery (except computers) | M63: Manufacturing | N63: 2.8906219
K64: US-CA | L64: Computers and relevant parts, conductors, measuring devices, communication devices | M64: Manufacturing | N64: 2.2469007
K65: RoUS | L65: Computers and relevant parts, conductors, measuring devices, communication devices | M65: Manufacturing | N65: 1.3961011
K66: RoW | L66: Computers and relevant parts, conductors, measuring devices, communication devices | M66: Manufacturing | N66: 30.263515
K67: US-CA | L67: Lights and light fixtures, switch boards, transformers, and home appliances | M67: Manufacturing | N67: 0.53732803
K68: RoUS | L68: Lights and light fixtures, switch boards, transformers, and home appliances | M68: Manufacturing | N68: 0.97589828
K69: RoW | L69: Lights and light fixtures, switch boards, transformers, and home appliances | M69: Manufacturing | N69: 2.6022672
K70: US-CA | L70: On-road vehicles (excluding motorcycles) and accompanying parts | M70: Manufacturing | N70: 1.6742462
K71: RoUS | L71: On-road vehicles (excluding motorcycles) and accompanying parts | M71: Manufacturing | N71: 4.9715159
K72: RoW | L72: On-road vehicles (excluding motorcycles) and accompanying parts | M72: Manufacturing | N72: 5.0190148
... K228: RoW | L228: Scrap, used and secondhand goods | M228: Used | N228: 2.9189584

Sheet Sector Codes
A1: Aggregate Category | B1: Code | C1: Name
A2: Agriculture | B2: 111CA | C2: Oilseeds, grains, vegetables, fruits, animal farms and aquaculture
A3: Agriculture | B3: 113FF | C3: Raw forest products, wild-caught fish and game, agriculture and forestry support
A4: Mining | B4: 211 | C4: Unrefined oil and gas
A5: Mining | B5: 212 | C5: Metal ores, dimensional stone, nonmetallic minerals
A6: Mining | B6: 213 | C6: Well drilling and support activities for mining
A7: Utilities | B7: 22 | C7: Electricity, natural gas, drinking water, and wastewater treatment
A8: Construction | B8: 23 | C8: Construction
A9: Manufacturing | B9: 321 | C9: Wood products (e.g. plywood, veneer)
A10: Manufacturing | B10: 327 | C10: Clay, glass, cement, concrete, and other nonmetallic mineral products
A11: Manufacturing | B11: 331 | C11: Primary and secondary ferrous and nonferrous metals
A12: Manufacturing | B12: 332 | C12: Fabricated metal products (e.g. architectural and structural metal products)
A13: Manufacturing | B13: 333 | C13: Machinery (except computers)
A14: Manufacturing | B14: 334 | C14: Computers and relevant parts, conductors, measuring devices, communication devices
A15: Manufacturing | B15: 335 | C15: Lights and light fixtures, switch boards, transformers, and home appliances
A16: Manufacturing | B16: 3361MV | C16: On-road vehicles (excluding motorcycles) and accompanying parts
A17: Manufacturing | B17: 3364OT | C17: Other vehicles (e.g. aircraft, water vessels), missiles, and accompanying parts
A18: Manufacturing | B18: 337 | C18: Furniture and shelving
A19: Manufacturing | B19: 339 | C19: Medical supplies, entertainment and sporting goods, fashion goods, advertising products
A20: Manufacturing | B20: 311FT | C20: Food and beverage and tobacco products
A21: Manufacturing | B21: 313TT | C21: Textiles and textile-derived products (except clothes)
A22: Manufacturing | B22: 315AL | C22: Clothing and leather
A23: Manufacturing | B23: 322 | C23: Paper products and paper production facilities
A24: Manufacturing | B24: 323 | C24: Print media and printing support
A25: Manufacturing | B25: 324 | C25: Petroleum fuels, asphalt, and other petroleum and coal products
A26: Manufacturing | B26: 325 | C26: Agricultural, pharmaceutical, industrial, and commercial chemicals
A27: Manufacturing | B27: 326 | C27: Plastics and rubber products
A28: Wholesale trade | B28: 42 | C28: Wholesale trade
A29: Retail trade | B29: 441 | C29: Vehicles and parts sales
A30: Retail trade | B30: 445 | C30: Food and beverage stores
A31: Retail trade | B31: 452 | C31: General merchandise stores
A32: Retail trade | B32: 4A0 | C32: Other retail
A33: Transportation and warehousing | B33: 481 | C33: Air transport
A34: Transportation and warehousing | B34: 482 | C34: Rail transport
A35: Transportation and warehousing | B35: 483 | C35: Water transport (boats, ships, ferries)
A36: Transportation and warehousing | B36: 484 | C36: Truck transport
A37: Transportation and warehousing | B37: 485 | C37: Passenger ground transport
A38: Transportation and warehousing | B38: 486 | C38: Pipeline transport
A39: Transportation and warehousing | B39: 487OS | C39: Couriers, messengers, transportation for leisure activities
A40: Transportation and warehousing | B40: 493 | C40: Warehouses
A41: Information | B41: 511 | C41: Media, literature, and software
A42: Information | B42: 512 | C42: Film and sound-based entertainment
A43: Information | B43: 513 | C43: Radio, TV, telecommunication
A44: Information | B44: 514 | C44: Data processing, internet publishing, and other information services
A45: Finance, insurance, real estate, rental, and leasing | B45: 521CI | C45: Monetary authorities, depository and nondepository credit intermediation and related activities
A46: Finance, insurance, real estate, rental, and leasing | B46: 523 | C46: Financial investments, exchanges, and advising
A47: Finance, insurance, real estate, rental, and leasing | B47: 524 | C47: Insurance agencies, carriers, and brokerages
A48: Finance, insurance, real estate, rental, and leasing | B48: 525 | C48: Funds, trusts, and financial vehicles
A49: Finance, insurance, real estate, rental, and leasing | B49: HS | C49: Housing
A50: Finance, insurance, real estate, rental, and leasing | B50: ORE | C50: Other real estate
A51: Finance, insurance, real estate, rental, and leasing | B51: 532RL | C51: Renting and leasing of goods, equipment, vehicles and nonfinancial intangible assets
A52: Professional and business services | B52: 5411 | C52: Legal services
A53: Professional and business services | B53: 5415 | C53: Computer programming and systems design
A54: Professional and business services | B54: 5412OP | C54: Miscellaneous professional, scientific, and technical services
A55: Professional and business services | B55: 55 | C55: Company and enterprise management
A56: Professional and business services | B56: 561 | C56: Administrative and support services
A57: Professional and business services | B57: 562 | C57: Waste management and remediation services
A58: Educational services, health care, and social assistance | B58: 61 | C58: Educational institutions and services
A59: Educational services, health care, and social assistance | B59: 621 | C59: Healthcare professions, laboratories, and ambulances
A60: Educational services, health care, and social assistance | B60: 622 | C60: Hospitals
A61: Educational services, health care, and social assistance | B61: 623 | C61: Nursing, community, mental health, and substance abuse facilities
A62: Educational services, health care, and social assistance | B62: 624 | C62: Child day care, community food services, housing services, and other relief services
A63: Arts, entertainment, recreation, accommodation, and food services | B63: 711AS | C63: Performing arts, spectator sports, museums, and related activities
A64: Arts, entertainment, recreation, accommodation, and food services | B64: 713 | C64: Amusement facilities, gambling facilities, resort and recreation facilities
A65: Arts, entertainment, recreation, accommodation, and food services | B65: 721 | C65: Hotels and campgrounds
A66: Arts, entertainment, recreation, accommodation, and food services | B66: 722 | C66: Food and beverage establishments
A67: Other services, except government | B67: 81 | C67: Other services, except government
A68: Government | B68: GFGD | C68: Federal general government (defense)
A69: Government | B69: GFGN | C69: Federal general government (nondefense)
A70: Government | B70: GFE | C70: Federal electric utilities and postal service
A71: Government | B71: GSLG | C71: State and local general government
A72: Government | B72: GSLE | C72: Other state and local government enterprises including transit and utilities
A73: Used | B73: Used | C73: Scrap, used and secondhand goods
A74: Other | B74: Other | C74: Noncomparable imports and rest-of-the-world adjustment
